{"BaseModel.aaca4aab-16ed-4c20-846a-ed17cc16bb6c": {"id": "aaca4aab-16ed-4c20-846a-ed17cc16bb6c", "created_at": "2024-05-18T06:44:02.111242", "updated_at": "2024-05-18T06:44:02.111244", "name": "My_First_Model", "my_number": 89, "__class__": "BaseModel"}, "BaseModel.55b16bec-8334-4ea7-84ee-6f1bc43d9e1b": {"id": "aaca4aab-16ed-4c20-846a-ed17cc16bb6c", "created_at": "2024-05-18T06:44:02.111242", "updated_at": "2024-05-18T06:44:02.111244", "name": "My_First_Model", "my_number": 89, "__class__": "BaseModel"}, "BaseModel.53318858-9528-45f9-9cd3-15edb625b403": {"id": "53318858-9528-45f9-9cd3-15edb625b403", "created_at": "2024-05-18T06:44:02.111412", "updated_at": "2024-05-18T06:44:02.111416", "name": "My_First_Model", "my_number": 89, "__class__": "BaseModel"}}